sonouno_server/__init__.py
sonouno_server/app.py
sonouno_server/config.py
sonouno_server/executors.py
sonouno_server/jwt.py
sonouno_server/main.py
sonouno_server/models/__init__.py
sonouno_server/models/iam.py
sonouno_server/models/jobs.py
sonouno_server/models/system.py
sonouno_server/models/transforms.py
sonouno_server/models/users.py
sonouno_server/models/variables.py
sonouno_server/routes/__init__.py
sonouno_server/routes/iam.py
sonouno_server/routes/jobs.py
sonouno_server/routes/system.py
sonouno_server/routes/transforms.py
sonouno_server/routes/users.py
sonouno_server/schemas.py
sonouno_server/types.py
sonouno_server/util/__init__.py
sonouno_server/util/call_dependencies.py
sonouno_server/util/current_user.py
sonouno_server/util/encoders.py
sonouno_server/util/io.py
sonouno_server/util/job_builder.py
sonouno_server/util/mail.py
sonouno_server/util/minio.py
sonouno_server/util/password.py
sonouno_server/util/transform_builder.py
sonouno_server-0.4.3.dist-info/WHEEL
sonouno_server-0.4.3.dist-info/METADATA
sonouno_server-0.4.3.dist-info/RECORD
